atmoregime/__init__.py
atmoregime/clustering.py
atmoregime/deseasonaliser.py
atmoregime/example.py
atmoregime/preprocessing.py
atmoregime/util.py
atmoregime-0.0.4.data/data/data/test_data.csv
atmoregime-0.0.4.dist-info/LICENSE
atmoregime-0.0.4.dist-info/METADATA
atmoregime-0.0.4.dist-info/WHEEL
atmoregime-0.0.4.dist-info/top_level.txt
atmoregime-0.0.4.dist-info/RECORD
